Workbook

Sheet Ringkasan Proyek
B2: STUDI KELAYAKAN BISNIS (SKB) - ETHEREAL HIJAB
B4: Pemilik Usaha: | C4: Meutia
B5: NPM: | C5: 062140612888
B6: Kelas: | C6: 8 BPA
B8: Daftar Produk & Harga Jual:
B9: ID | C9: Nama Produk | D9: Harga Jual (IDR)
B10: 1 | C10: Ethereal Voal Square Premium | D10: 85000
B11: 2 | C11: Silk Pashmina Shimmer | D11: 110000
B12: 3 | C12: Bergo Maryam Instant Daily | D12: 45000
B13: 4 | C13: Pashmina Inner 2-in-1 Ethereal | D13: 75000
B14: 5 | C14: Turban Instant Pleated | D14: 55000
B15: 6 | C15: Sport Hijab Active Air | D15: 60000
B16: 7 | C16: Ciput Rajut Anti Bingung | D16: 20000

Sheet Investasi Awal
B2: BIAYA INVESTASI AWAL - ETHEREAL HIJAB
B4: No | C4: Uraian Kebutuhan | D4: Kuantitas | E4: Harga Satuan (IDR) | F4: Jumlah Biaya (IDR)
B5: 1 | C5: Mesin Jahit Juki High Speed | D5: 2 | E5: 4500000 | F5: =D5*E5
B6: 2 | C6: Mesin Obras Benang 4 | D6: 1 | E6: 3500000 | F6: =D6*E6
B7: 3 | C7: Gunting Kain Elektrik | D7: 1 | E7: 800000 | F7: =D7*E7
B8: 4 | C8: Setrika Uap / Steamer | D8: 1 | E8: 1200000 | F8: =D8*E8
B9: 5 | C9: Manekin Set Hanger | D9: 5 | E9: 200000 | F9: =D9*E9
B10: 6 | C10: Sewa Workshop & Butik (1 Tahun) | D10: 1 | E10: 20000000 | F10: =D10*E10
B11: 7 | C11: Renovasi Interior Butik | D11: 1 | E11: 5000000 | F11: =D11*E11
B12: 8 | C12: Papan Nama Acrylic & LED | D12: 1 | E12: 1500000 | F12: =D12*E12
B13: 9 | C13: Laptop Administrasi Kasir | D13: 1 | E13: 4000000 | F13: =D13*E13
B14: 10 | C14: Biaya Legalitas & Izin Usaha | D14: 1 | E14: 2000000 | F14: =D14*E14
B15: 11 | C15: Kas Awal / Modal Kerja Operasional | D15: 1 | E15: 10000000 | F15: =D15*E15
C16: TOTAL INVESTASI AWAL | F16: =SUM(F5:F15)

Sheet HPP & Biaya Variabel
B2: BIAYA PRODUKSI & MARGIN HPP
B4: No | C4: Nama Hijab | D4: Bahan Baku (IDR) | E4: Packaging & Label (IDR) | F4: Tenaga Kerja Jahit (IDR) | G4: Total HPP (IDR) | H4: Harga Jual (IDR) | I4: Margin Laba (IDR)
B5: 1 | C5: Ethereal Voal Square Premium | D5: 22000 | E5: 4000 | F5: 9000 | G5: =SUM(D5:F5) | H5: 85000 | I5: =H5-G5
B6: 2 | C6: Silk Pashmina Shimmer | D6: 28000 | E6: 4000 | F6: 10000 | G6: =SUM(D6:F6) | H6: 110000 | I6: =H6-G6
B7: 3 | C7: Bergo Maryam Instant Daily | D7: 11000 | E7: 3000 | F7: 6000 | G7: =SUM(D7:F7) | H7: 45000 | I7: =H7-G7
B8: 4 | C8: Pashmina Inner 2-in-1 Ethereal | D8: 19000 | E8: 4000 | F8: 9000 | G8: =SUM(D8:F8) | H8: 75000 | I8: =H8-G8
B9: 5 | C9: Turban Instant Pleated | D9: 13000 | E9: 3000 | F9: 7000 | G9: =SUM(D9:F9) | H9: 55000 | I9: =H9-G9
B10: 6 | C10: Sport Hijab Active Air | D10: 15000 | E10: 3000 | F10: 7000 | G10: =SUM(D10:F10) | H10: 60000 | I10: =H10-G10
B11: 7 | C11: Ciput Rajut Anti Bingung | D11: 4000 | E11: 2000 | F11: 3000 | G11: =SUM(D11:F11) | H11: 20000 | I11: =H11-G11

Sheet Arus Kas
B2: PROYEKSI ARUS KAS 12 BULAN (TAHUNAN) - ETHEREAL HIJAB
B4: Uraian / Bulan | C4: Bulan 1 | D4: Bulan 2 | E4: Bulan 3 | F4: Bulan 4 | G4: Bulan 5 | H4: Bulan 6 | I4: Bulan 7 | J4: Bulan 8 | K4: Bulan 9 | L4: Bulan 10 | M4: Bulan 11 | N4: Bulan 12
B5: Penerimaan Kas (Omset) | C5: 1619500 | D5: 1700475 | E5: 1732865 | F5: 1781450 | G5: 1813840 | H5: 1862425 | I5: 1894815 | J5: 1943400 | K5: 1975790 | L5: 2024375 | M5: 2056765 | N5: 2105350
B6: Pengeluaran Kas:
B7: - HPP Bahan & Produksi | C7: 728775 | D7: 748209 | E7: 745132 | F7: 748209 | G7: 761813 | H7: 763594 | I7: 776874 | J7: 777360 | K7: 790316 | L7: 789506 | M7: 802138 | N7: 800033
B8: - Operasional & Gaji | C8: 12000000 | D8: 12200000 | E8: 12500000 | F8: 12800000 | G8: 13000000 | H8: 13200000 | I8: 13500000 | J8: 13800000 | K8: 14000000 | L8: 14200000 | M8: 14500000 | N8: 14800000
B9: - Pemasaran / Iklan | C9: 3000000 | D9: 3100000 | E9: 3200000 | F9: 3300000 | G9: 3400000 | H9: 3500000 | I9: 3600000 | J9: 3700000 | K9: 3800000 | L9: 3900000 | M9: 4000000 | N9: 4100000
B10: Total Pengeluaran Kas | C10: =SUM(C7:C9) | D10: =SUM(D7:D9) | E10: =SUM(E7:E9) | F10: =SUM(F7:F9) | G10: =SUM(G7:G9) | H10: =SUM(H7:H9) | I10: =SUM(I7:I9) | J10: =SUM(J7:J9) | ... N10: =SUM(N7:N9)
B11: Surplus / Arus Kas Bersih | C11: =C5-C10 | D11: =D5-D10 | E11: =E5-E10 | F11: =F5-F10 | G11: =G5-G10 | H11: =H5-H10 | I11: =I5-I10 | J11: =J5-J10 | ... N11: =N5-N10

Sheet Analisis Kelayakan
B2: ANALISIS KELAYAKAN INVESTASI - ETHEREAL HIJAB
B4: 1. Accounting Rate of Return (ARR)
B5: Investasi Awal (Io) | C5: ='Investasi Awal'!F16
B6: Rata-rata Laba Bersih Per Bulan | C6: =AVERAGE('Arus Kas'!C11:N11)
B7: ARR (Tahunan) | C7: =(C6*12)/C5
B9: 2. Payback Period (PP)
B10: Akumulasi Kas Masuk Bulan 1 | C10: ='Arus Kas'!C11
B11: Akumulasi Kas Masuk Bulan 2 | C11: ='Arus Kas'!C11+'Arus Kas'!D11
B12: Payback Period (Bulan) | C12: =C5/C6
B14: 3. Net Present Value (NPV) & Profitability Index (PI)
B15: Discount Rate (Suku Bunga) | C15: 0.12
B16: Total PV of Cash Flows | C16: =NPV(C15, 'Arus Kas'!C11:N11)
B17: Net Present Value (NPV) | C17: =C16-C5
B18: Profitability Index (PI) | C18: =C16/C5
